draft2inspiration/prompt.md
draft2inspiration/server.py
draft2inspiration-0.1.0.dist-info/METADATA
draft2inspiration-0.1.0.dist-info/WHEEL
draft2inspiration-0.1.0.dist-info/entry_points.txt
draft2inspiration-0.1.0.dist-info/RECORD
