Metadata-Version: 2.3
Name: draft2inspiration
Version: 0.1.0
Summary: 获取用户给出的离散草稿灵感集，发散出可用的灵感。
License: MIT
Author: GZT
Author-email: ave1age@163.com
Requires-Python: >=3.10
Classifier: License :: OSI Approved :: MIT License
Classifier: Programming Language :: Python :: 3
Classifier: Programming Language :: Python :: 3.10
Classifier: Programming Language :: Python :: 3.11
Classifier: Programming Language :: Python :: 3.12
Classifier: Programming Language :: Python :: 3.13
Requires-Dist: mcp (>=1.9.4)
